Q1/ALUmain.v
//	DIBYADARSHAN HOTA AND OMKAR PRABHU


//	1-bit ALU. Build a 1-bit ALU that can perform the following logical and arithmetic operations: AND, OR, NAND,
//	NOR, ADD, SUBTRACT. Include two additional flags: (a) a flag to indicate if the result of the ALU operation is
//	zero (Z), (b) a flag to indicate if the first input is greater than the second input.


//	Main module for the ALU
module 	alu (opcode,input1,input2,carryin,flag1,flag2,out,carryout);
//	opcode represents the opcode 
input[2:0] opcode;
//	input1 represents the 1st input
input input1;
//	input2 represents the 2nd input
input input2;
//	carryin represents the carry in given
input carryin;
//	flag1 checks if the output bit is 0
output reg flag1;
//	flag2 checks if 1st input is greater
output reg flag2;
//	out represents the output bit
output reg out;
//	carryout represents the carry out
output reg carryout;
	
	//	BEHAVIORAL MODELLING OF ALU
	always@(input1,input2,carryin,opcode) begin
		
		//	assigning value to the flag which checks if input 1 is greater
    		flag2 = input1 & (~input2);		
	
		//	if ladder to check which operation is to be done
		//	After that values are assigned to carryout and out	
		
/*
	OPCODES for different functions (3 bit)

		ADD: 		000

		SUBTRACT: 	001

		AND operation: 	010

		OR operation: 	011

		NAND operation:	100

		NOR operation:	101

*/



		if(opcode==3'b000) begin
			{carryout,out}=input1+input2+carryin;		
		end

		if(opcode==3'b001) begin
			{carryout,out}=input1-input2-carryin;							
		end

		if(opcode==3'b010) begin
			out=input1&input2;			
		end

		if(opcode==3'b011) begin
			out=input1|input2;
		end

		if(opcode==3'b100) begin
			out=~(input1&input2);
		end

		if(opcode==3'b101) begin
			out=~(input1|input2);
		end	

		//	assigning value to the flag which checks if the output is 0
		flag1=~out;
	end
		
endmodule

Q1/t_ALU.v
//	DIBYADARSHAN HOTA AND OMKAR PRABHU


//	1-bit ALU. Build a 1-bit ALU that can perform the following logical and arithmetic operations: AND, OR, NAND,
//	NOR, ADD, SUBTRACT. Include two additional flags: (a) a flag to indicate if the result of the ALU operation is
//	zero (Z), (b) a flag to indicate if the first input is greater than the second input.


//	TESTBENCH FOR 1 BIT ALU
`timescale 1ns / 100ps 
module stimulus; 
/*
	OPCODES for different functions (3 bit)

		ADD: 		000

		SUBTRACT: 	001

		AND operation: 	010

		OR operation: 	011

		NAND operation:	100

		NOR operation:	101

*/
reg[3:1] opcode;
//	input1 for 1st input
reg input1;
//	input2 for 2nd input 
reg input2;
//	carryin for adder and subtractor
reg carryin;
//	flag1 to check if result is 0
wire flag1;
//	flag to check if 1st input is greater
wire flag2;
//	out is the output
wire out;
//	carryout for adder and subtractor
wire carryout;

//	Instantiation
	alu inst(opcode,input1,input2,carryin,flag1,flag2,out,carryout);
	
	initial begin

		//	Creating the gtkwave	
		$dumpfile("ALU.vcd");
    		$dumpvars(0,stimulus);

		$display("\n1 BIT ALU\nOPCODES ADD:000, SUBTRACT:001, AND:010, OR:011 ,NAND:100, NOR:101\n");

		//	Giving all the possible inputs to the main module
		opcode=4'b000;input1=0;input2=0;carryin=0;
		#5
		opcode=4'b000;input1=0;input2=0;carryin=1;
		#5
		opcode=4'b000;input1=0;input2=1;carryin=0;
		#5
		opcode=4'b000;input1=0;input2=1;carryin=1;
		#5
		opcode=4'b000;input1=1;input2=0;carryin=0;
		#5
		opcode=4'b000;input1=1;input2=0;carryin=1;
		#5
		opcode=4'b000;input1=1;input2=1;carryin=0;
		#5
		opcode=4'b000;input1=1;input2=1;carryin=1;
		#5
		$display("\nOPCODES ADD:000, SUBTRACT:001, AND:010, OR:011 ,NAND:100, NOR:101\n");
		
		#5
		opcode=4'b001;input1=0;input2=0;carryin=0;
		#5
		opcode=4'b001;input1=0;input2=0;carryin=1;
		#5
		opcode=4'b001;input1=0;input2=1;carryin=0;
		#5
		opcode=4'b001;input1=0;input2=1;carryin=1;
		#5
		opcode=4'b001;input1=1;input2=0;carryin=0;
		#5
		opcode=4'b001;input1=1;input2=0;carryin=1;
		#5
		opcode=4'b001;input1=1;input2=1;carryin=0;
		#5
		opcode=4'b001;input1=1;input2=1;carryin=1;
		#5
		$display("\nOPCODES ADD:000, SUBTRACT:001, AND:010, OR:011 ,NAND:100, NOR:101\n");
		
		#5
		carryin=1'bx;
		opcode=4'b010;input1=0;input2=0;
		#5
		opcode=4'b010;input1=0;input2=1;
		#5
		opcode=4'b010;input1=1;input2=0;
		#5
		opcode=4'b010;input1=1;input2=1;
		#5
		$display("\nOPCODES ADD:000, SUBTRACT:001, AND:010, OR:011 ,NAND:100, NOR:101\n");
		
		#5
		opcode=4'b011;input1=0;input2=0;
		#5
		opcode=4'b011;input1=0;input2=1;
		#5
		opcode=4'b011;input1=1;input2=0;
		#5
		opcode=4'b011;input1=1;input2=1;
		#5
		$display("\nOPCODES ADD:000, SUBTRACT:001, AND:010, OR:011 ,NAND:100, NOR:101\n");
		
		#5
		opcode=4'b100;input1=0;input2=0;
		#5
		opcode=4'b100;input1=0;input2=1;
		#5
		opcode=4'b100;input1=1;input2=0;
		#5
		opcode=4'b100;input1=1;input2=1;
		#5
		$display("\nOPCODES ADD:000, SUBTRACT:001, AND:010, OR:011 ,NAND:100, NOR:101\n");
		
		#5
		opcode=4'b101;input1=0;input2=0;
		#5
		opcode=4'b101;input1=0;input2=1;
		#5
		opcode=4'b101;input1=1;input2=0;
		#5
		opcode=4'b101;input1=1;input2=1;
		
		#5
		$finish;
	end
	
initial begin
//	Printing all the vaules via $monitor statement
$monitor("OPCODE:%3b input1:%b, input2:%b, carry in:%b, carry out:%b, output:%b, isResult0:%b, isFirstInputGreater:%b",opcode,input1,input2,carryin,carryout,out,flag1,flag2); 
end

endmodule

Q1/ALU.vcd
$date
	Tue Oct 31 20:31:28 2017
$end
$version
	Icarus Verilog
$end
$timescale
	100ps
$end
$scope module stimulus $end
$var wire 1 ! carryout $end
$var wire 1 " flag1 $end
$var wire 1 # flag2 $end
$var wire 1 $ out $end
$var reg 1 % carryin $end
$var reg 1 & input1 $end
$var reg 1 ' input2 $end
$var reg 3 ( opcode [3:1] $end
$scope module inst $end
$var wire 1 ) carryin $end
$var wire 1 * input1 $end
$var wire 1 + input2 $end
$var wire 3 , opcode [2:0] $end
$var reg 1 - carryout $end
$var reg 1 . flag1 $end
$var reg 1 / flag2 $end
$var reg 1 0 out $end
$upscope $end
$upscope $end
$enddefinitions $end
#0
$dumpvars
00
0/
1.
0-
b0 ,
0+
0*
0)
b0 (
0'
0&
0%
0$
0#
1"
0!
$end
#50
0.
0"
10
1$
1%
1)
#100
0%
0)
1'
1+
#150
1.
1"
1-
1!
00
0$
1%
1)
#200
0.
0"
0-
0!
10
1$
1/
1#
0%
0)
0'
0+
1&
1*
#250
1.
1"
1-
1!
00
0$
1%
1)
#300
0/
0#
0%
0)
1'
1+
#350
0.
0"
10
1$
1%
1)
#450
1.
1"
0-
0!
00
0$
0%
0)
0'
0+
0&
0*
b1 (
b1 ,
#500
0.
0"
1-
1!
10
1$
1%
1)
#550
0%
0)
1'
1+
#600
1.
1"
00
0$
1%
1)
#650
0.
0"
0-
0!
10
1$
1/
1#
0%
0)
0'
0+
1&
1*
#700
1.
1"
00
0$
1%
1)
#750
0/
0#
0%
0)
1'
1+
#800
0.
0"
1-
1!
10
1$
1%
1)
#900
1.
1"
00
0$
0'
0+
0&
0*
b10 (
b10 ,
x%
x)
#950
1'
1+
#1000
1/
1#
0'
0+
1&
1*
#1050
0.
0"
10
1$
0/
0#
1'
1+
#1150
1.
1"
00
0$
0'
0+
0&
0*
b11 (
b11 ,
#1200
0.
0"
10
1$
1'
1+
#1250
1/
1#
0'
0+
1&
1*
#1300
0/
0#
1'
1+
#1400
0'
0+
0&
0*
b100 (
b100 ,
#1450
1'
1+
#1500
1/
1#
0'
0+
1&
1*
#1550
1.
1"
00
0$
0/
0#
1'
1+
#1650
0.
0"
10
1$
0'
0+
0&
0*
b101 (
b101 ,
#1700
1.
1"
00
0$
1'
1+
#1750
1/
1#
0'
0+
1&
1*
#1800
0/
0#
1'
1+
