Q2/RegisterFile.v
/**
*	Module for Register File
*	By: Omkar Prabhu 16CO233
*	28th October 2017
*/

`timescale 1ns/100ps


module RegisterFile (input write, input [0:31] reg_data, input [0:4] register_no, input [0:4] readReg1, input[0:4]  readReg2, output reg [0:31] readData1, output reg [0:31] readData2);

    reg [0:31] data_write1; reg [0:31] data_write2; reg [0:31] data_write3; reg [0:31] data_write4; reg [0:31] data_write5; reg [0:31] data_write6; reg [0:31] data_write7; reg [0:31] data_write8; reg [0:31] data_write9; reg [0:31] data_write10; reg [0:31] data_write11; reg [0:31] data_write12; reg [0:31] data_write13; reg [0:31] data_write14; reg [0:31] data_write15; reg [0:31] data_write16; reg [0:31] data_write17; reg [0:31] data_write18; reg [0:31] data_write19; reg [0:31] data_write20; reg [0:31] data_write21; reg [0:31] data_write22; reg [0:31] data_write23; reg [0:31] data_write24; reg [0:31] data_write25; reg [0:31] data_write26; reg [0:31] data_write27; reg [0:31] data_write28; reg [0:31] data_write29; reg [0:31] data_write30; reg [0:31] data_write31; reg [0:31] data_write32;
    wire [0:31] out1; wire [0:31] out2; wire [0:31] out3; wire [0:31] out4; wire [0:31] out5; wire [0:31] out6; wire [0:31] out7; wire [0:31] out8; wire [0:31] out9; wire [0:31] out10; wire [0:31] out11; wire [0:31] out12; wire [0:31] out13; wire [0:31] out14; wire [0:31] out15; wire [0:31] out16; wire [0:31] out17; wire [0:31] out18; wire [0:31] out19; wire [0:31] out20; wire [0:31] out21; wire [0:31] out22; wire [0:31] out23; wire [0:31] out24; wire [0:31] out25; wire [0:31] out26; wire [0:31] out27; wire [0:31] out28; wire [0:31] out29; wire [0:31] out30; wire [0:31] out31; wire [0:31] out32;
    reg write1, write2, write3, write4, write5, write6, write7, write8, write9, write10, write11, write12, write13, write14, write15, write16, write17, write18, write19, write20, write21, write22, write23, write24, write25, write26, write27, write28, write29, write30, write31, write32;

    // 32 Registers in the Register file
    rg32b rg1 (data_write1, write1, out1);
    rg32b rg2 (data_write2, write2, out2);
    rg32b rg3 (data_write3, write3, out3);
    rg32b rg4 (data_write4, write4, out4);
    rg32b rg5 (data_write5, write5, out5);
    rg32b rg6 (data_write6, write6, out6);
    rg32b rg7 (data_write7, write7, out7);
    rg32b rg8 (data_write8, write8, out8);
    rg32b rg9 (data_write9, write9, out9);
    rg32b rg10 (data_write10, write10, out10);
    rg32b rg11 (data_write11, write11, out11);
    rg32b rg12 (data_write12, write12, out12);
    rg32b rg13 (data_write13, write13, out13);
    rg32b rg14 (data_write14, write14, out14);
    rg32b rg15 (data_write15, write15, out15);
    rg32b rg16 (data_write16, write16, out16);
    rg32b rg17 (data_write17, write17, out17);
    rg32b rg18 (data_write18, write18, out18);
    rg32b rg19 (data_write19, write19, out19);
    rg32b rg20 (data_write20, write20, out20);
    rg32b rg21 (data_write21, write21, out21);
    rg32b rg22 (data_write22, write22, out22);
    rg32b rg23 (data_write23, write23, out23);
    rg32b rg24 (data_write24, write24, out24);
    rg32b rg25 (data_write25, write25, out25);
    rg32b rg26 (data_write26, write26, out26);
    rg32b rg27 (data_write27, write27, out27);
    rg32b rg28 (data_write28, write28, out28);
    rg32b rg29 (data_write29, write29, out29);
    rg32b rg30 (data_write30, write30, out30);
    rg32b rg31 (data_write31, write31, out31);
    rg32b rg32 (data_write32, write32, out32);
    
    
    always @ (write or register_no or readReg1 or readReg2 or reg_data) begin

        // check write signal
        if(write == 1'b1) begin
            // Decode register address
            case (register_no)
                5'b00000: begin write1 <= 1'b1; data_write1 <= reg_data; end
                5'b00001: begin write2 <= 1'b1; data_write2 <= reg_data; end
                5'b00010: begin write3 <= 1'b1; data_write3 <= reg_data; end
                5'b00011: begin write4 <= 1'b1; data_write4 <= reg_data; end
                5'b00100: begin write5 <= 1'b1; data_write5 <= reg_data; end
                5'b00101: begin write6 <= 1'b1; data_write6 <= reg_data; end
                5'b00110: begin write7 <= 1'b1; data_write7 <= reg_data; end
                5'b00111: begin write8 <= 1'b1; data_write8 <= reg_data; end
                5'b01000: begin write9 <= 1'b1; data_write9 <= reg_data; end
                5'b01001: begin write10 <= 1'b1; data_write10 <= reg_data; end
                5'b01010: begin write11 <= 1'b1; data_write11 <= reg_data; end
                5'b01011: begin write12 <= 1'b1; data_write12 <= reg_data; end
                5'b01100: begin write13 <= 1'b1; data_write13 <= reg_data; end
                5'b01101: begin write14 <= 1'b1; data_write14 <= reg_data; end
                5'b01110: begin write15 <= 1'b1; data_write15 <= reg_data; end
                5'b01111: begin write16 <= 1'b1; data_write16 <= reg_data; end
                5'b10000: begin write17 <= 1'b1; data_write17 <= reg_data; end
                5'b10001: begin write18 <= 1'b1; data_write18 <= reg_data; end
                5'b10010: begin write19 <= 1'b1; data_write19 <= reg_data; end
                5'b10011: begin write20 <= 1'b1; data_write20 <= reg_data; end
                5'b10100: begin write21 <= 1'b1; data_write21 <= reg_data; end
                5'b10101: begin write22 <= 1'b1; data_write22 <= reg_data; end
                5'b10110: begin write23 <= 1'b1; data_write23 <= reg_data; end
                5'b10111: begin write24 <= 1'b1; data_write24 <= reg_data; end
                5'b11000: begin write25 <= 1'b1; data_write25 <= reg_data; end
                5'b11001: begin write26 <= 1'b1; data_write26 <= reg_data; end
                5'b11010: begin write27 <= 1'b1; data_write27 <= reg_data; end
                5'b11011: begin write28 <= 1'b1; data_write28 <= reg_data; end
                5'b11100: begin write29 <= 1'b1; data_write29 <= reg_data; end
                5'b11101: begin write30 <= 1'b1; data_write30 <= reg_data; end
                5'b11110: begin write31 <= 1'b1; data_write31 <= reg_data; end
                5'b11111: begin write32 <= 1'b1; data_write32 <= reg_data; end
            endcase    
        end
        
        else begin
            // decode read Register 1 address 
            case (readReg1)
                5'b00000: begin write1 <= 1'b0; readData1 <= out1; end
                5'b00001: begin write2 <= 1'b0; readData1 <= out2; end
                5'b00010: begin write3 <= 1'b0; readData1 <= out3; end
                5'b00011: begin write4 <= 1'b0; readData1 <= out4; end
                5'b00100: begin write5 <= 1'b0; readData1 <= out5; end
                5'b00101: begin write6 <= 1'b0; readData1 <= out6; end
                5'b00110: begin write7 <= 1'b0; readData1 <= out7; end
                5'b00111: begin write8 <= 1'b0; readData1 <= out8; end
                5'b01000: begin write9 <= 1'b0; readData1 <= out9; end
                5'b01001: begin write10 <= 1'b0; readData1 <= out10; end
                5'b01010: begin write11 <= 1'b0; readData1 <= out11; end
                5'b01011: begin write12 <= 1'b0; readData1 <= out12; end
                5'b01100: begin write13 <= 1'b0; readData1 <= out13 ; end
                5'b01101: begin write14 <= 1'b0; readData1 <= out14 ; end
                5'b01110: begin write15 <= 1'b0; readData1 <= out15 ; end
                5'b01111: begin write16 <= 1'b0; readData1 <= out16 ; end
                5'b10000: begin write17 <= 1'b0; readData1 <= out17 ; end
                5'b10001: begin write18 <= 1'b0; readData1 <= out18 ; end
                5'b10010: begin write19 <= 1'b0; readData1 <= out19 ; end
                5'b10011: begin write20 <= 1'b0; readData1 <= out20; end
                5'b10100: begin write21 <= 1'b0; readData1 <= out21; end
                5'b10101: begin write22 <= 1'b0; readData1 <= out22; end
                5'b10110: begin write23 <= 1'b0; readData1 <= out23; end
                5'b10111: begin write24 <= 1'b0; readData1 <= out24; end
                5'b11000: begin write25 <= 1'b0; readData1 <= out25; end
                5'b11001: begin write26 <= 1'b0; readData1 <= out26; end
                5'b11010: begin write27 <= 1'b0; readData1 <= out27; end
                5'b11011: begin write28 <= 1'b0; readData1 <= out28; end
                5'b11100: begin write29 <= 1'b0; readData1 <= out29; end
                5'b11101: begin write30 <= 1'b0; readData1 <= out30; end
                5'b11110: begin write31 <= 1'b0; readData1 <= out31; end
                5'b11111: begin write32 <= 1'b0; readData1 <= out32; end
            endcase   

            // decode read Register 2 address
            case (readReg2)
                5'b00000: begin write1 <= 1'b0; readData2 <= out1; end
                5'b00001: begin write2 <= 1'b0; readData2 <= out2; end
                5'b00010: begin write3 <= 1'b0; readData2 <= out3; end
                5'b00011: begin write4 <= 1'b0; readData2 <= out4; end
                5'b00100: begin write5 <= 1'b0; readData2 <= out5; end
                5'b00101: begin write6 <= 1'b0; readData2 <= out6; end
                5'b00110: begin write7 <= 1'b0; readData2 <= out7; end
                5'b00111: begin write8 <= 1'b0; readData2 <= out8; end
                5'b01000: begin write9 <= 1'b0; readData2 <= out9; end
                5'b01001: begin write10 <= 1'b0; readData2 <= out10; end
                5'b01010: begin write11 <= 1'b0; readData2 <= out11; end
                5'b01011: begin write12 <= 1'b0; readData2 <= out12; end
                5'b01100: begin write13 <= 1'b0; readData2 <= out13; end
                5'b01101: begin write14 <= 1'b0; readData2 <= out14; end
                5'b01110: begin write15 <= 1'b0; readData2 <= out15; end
                5'b01111: begin write16 <= 1'b0; readData2 <= out16; end
                5'b10000: begin write17 <= 1'b0; readData2 <= out17; end
                5'b10001: begin write18 <= 1'b0; readData2 <= out18; end
                5'b10010: begin write19 <= 1'b0; readData2 <= out19; end
                5'b10011: begin write20 <= 1'b0; readData2 <= out20; end
                5'b10100: begin write21 <= 1'b0; readData2 <= out21; end
                5'b10101: begin write22 <= 1'b0; readData2 <= out22; end
                5'b10110: begin write23 <= 1'b0; readData2 <= out23; end
                5'b10111: begin write24 <= 1'b0; readData2 <= out24; end
                5'b11000: begin write25 <= 1'b0; readData2 <= out25; end
                5'b11001: begin write26 <= 1'b0; readData2 <= out26; end
                5'b11010: begin write27 <= 1'b0; readData2 <= out27; end
                5'b11011: begin write28 <= 1'b0; readData2 <= out28; end
                5'b11100: begin write29 <= 1'b0; readData2 <= out29; end
                5'b11101: begin write30 <= 1'b0; readData2 <= out30; end
                5'b11110: begin write31 <= 1'b0; readData2 <= out31; end
                5'b11111: begin write32 <= 1'b0; readData2 <= out32; end
            endcase    
        end
    end

endmodule

// 32 bit Register 
module rg32b (input [0:31] data_write , input write, output reg [0:31] data);
    
    // initialize data in registers
    initial begin
        data <= 32'b00000000000000000000000000000000;
    end

    always @ (write or data_write) begin
        // check write signal
        if (write == 1'b1) begin
            // write data
            data <= data_write;
        end
        else begin
            // memory state
            data <= data;
        end
    end

endmodule

Q2/t_RegisterFile.v
/**
*	Test bench for Register file
*	By: Omkar Prabhu 16CO233
*	28th October 2017
*/


`timescale 1ns/100ps

module t_RegisterFile;

    // output data
    wire [0:31] readData1;
    wire [0:31] readData2;

    // input signals
    reg write;
    reg [0:4] register_no, readReg1, readReg2;
    reg [0:31] reg_data;

    integer i;
    
    // Register file thread instantated
    RegisterFile inst ( write, reg_data, register_no, readReg1, readReg2, readData1, readData2);

    // input combinations
    initial begin

        $dumpfile("RegisterFile.vcd");
        $dumpvars(0, t_RegisterFile);
        
        // initial setting
        write = 1'b1;
        readReg1 = 5'b00000;
        readReg2 = 5'b00000;
        register_no = 5'b00000;
        reg_data = 32'b00000000000000000000000000000000;

        // loaded data in all registers of the register file
        for (i = 0; i < 31; i++) begin
            #1; write = 1'b0;
            #1;
            register_no = register_no + 1'b1;
            #1;
            reg_data = reg_data + 1'b1;
            #1; write = 1'b1;
        end

        #10;
        write = 1'b0;

        // read contents of two registers from register file
        #1;
        readReg1 = 5'b00000;
        #1;
        readReg2 = 5'b00001;

        // random loading of data into two registers of register file
        register_no = 5'b00000;
        reg_data = 32'b00111001110011100111111110011110;
        #10; 
        write = 1'b1;
        #10;
        write = 1'b0;

        #10;
        register_no = 5'b00001;
        reg_data = 32'b11000000000100000000010000100000;
        #10; 
        write = 1'b1;
        #10;
        write = 1'b0;

        // read contents of two registers from register file
        #1;
        readReg1 = 5'b00000;
        #1;
        readReg2 = 5'b00001;

        #30;
       
    end

    // display outputs
    initial begin
        // outputs are displayed in vcd file itself.
    end

endmodule

Q2/RegisterFile.vcd
$date
	Mon Oct 30 23:47:33 2017
$end
$version
	Icarus Verilog
$end
$timescale
	100ps
$end
$scope module t_RegisterFile $end
$var wire 32 ! readData2 [0:31] $end
$var wire 32 " readData1 [0:31] $end
$var reg 5 # readReg1 [0:4] $end
$var reg 5 $ readReg2 [0:4] $end
$var reg 32 % reg_data [0:31] $end
$var reg 5 & register_no [0:4] $end
$var reg 1 ' write $end
$var integer 32 ( i [31:0] $end
$scope module inst $end
$var wire 5 ) readReg1 [0:4] $end
$var wire 5 * readReg2 [0:4] $end
$var wire 32 + reg_data [0:31] $end
$var wire 5 , register_no [0:4] $end
$var wire 1 ' write $end
$var wire 32 - out9 [0:31] $end
$var wire 32 . out8 [0:31] $end
$var wire 32 / out7 [0:31] $end
$var wire 32 0 out6 [0:31] $end
$var wire 32 1 out5 [0:31] $end
$var wire 32 2 out4 [0:31] $end
$var wire 32 3 out32 [0:31] $end
$var wire 32 4 out31 [0:31] $end
$var wire 32 5 out30 [0:31] $end
$var wire 32 6 out3 [0:31] $end
$var wire 32 7 out29 [0:31] $end
$var wire 32 8 out28 [0:31] $end
$var wire 32 9 out27 [0:31] $end
$var wire 32 : out26 [0:31] $end
$var wire 32 ; out25 [0:31] $end
$var wire 32 < out24 [0:31] $end
$var wire 32 = out23 [0:31] $end
$var wire 32 > out22 [0:31] $end
$var wire 32 ? out21 [0:31] $end
$var wire 32 @ out20 [0:31] $end
$var wire 32 A out2 [0:31] $end
$var wire 32 B out19 [0:31] $end
$var wire 32 C out18 [0:31] $end
$var wire 32 D out17 [0:31] $end
$var wire 32 E out16 [0:31] $end
$var wire 32 F out15 [0:31] $end
$var wire 32 G out14 [0:31] $end
$var wire 32 H out13 [0:31] $end
$var wire 32 I out12 [0:31] $end
$var wire 32 J out11 [0:31] $end
$var wire 32 K out10 [0:31] $end
$var wire 32 L out1 [0:31] $end
$var reg 32 M data_write1 [0:31] $end
$var reg 32 N data_write10 [0:31] $end
$var reg 32 O data_write11 [0:31] $end
$var reg 32 P data_write12 [0:31] $end
$var reg 32 Q data_write13 [0:31] $end
$var reg 32 R data_write14 [0:31] $end
$var reg 32 S data_write15 [0:31] $end
$var reg 32 T data_write16 [0:31] $end
$var reg 32 U data_write17 [0:31] $end
$var reg 32 V data_write18 [0:31] $end
$var reg 32 W data_write19 [0:31] $end
$var reg 32 X data_write2 [0:31] $end
$var reg 32 Y data_write20 [0:31] $end
$var reg 32 Z data_write21 [0:31] $end
$var reg 32 [ data_write22 [0:31] $end
$var reg 32 \ data_write23 [0:31] $end
$var reg 32 ] data_write24 [0:31] $end
$var reg 32 ^ data_write25 [0:31] $end
$var reg 32 _ data_write26 [0:31] $end
$var reg 32 ` data_write27 [0:31] $end
$var reg 32 a data_write28 [0:31] $end
$var reg 32 b data_write29 [0:31] $end
$var reg 32 c data_write3 [0:31] $end
$var reg 32 d data_write30 [0:31] $end
$var reg 32 e data_write31 [0:31] $end
$var reg 32 f data_write32 [0:31] $end
$var reg 32 g data_write4 [0:31] $end
$var reg 32 h data_write5 [0:31] $end
$var reg 32 i data_write6 [0:31] $end
$var reg 32 j data_write7 [0:31] $end
$var reg 32 k data_write8 [0:31] $end
$var reg 32 l data_write9 [0:31] $end
$var reg 32 m readData1 [0:31] $end
$var reg 32 n readData2 [0:31] $end
$var reg 1 o write1 $end
$var reg 1 p write10 $end
$var reg 1 q write11 $end
$var reg 1 r write12 $end
$var reg 1 s write13 $end
$var reg 1 t write14 $end
$var reg 1 u write15 $end
$var reg 1 v write16 $end
$var reg 1 w write17 $end
$var reg 1 x write18 $end
$var reg 1 y write19 $end
$var reg 1 z write2 $end
$var reg 1 { write20 $end
$var reg 1 | write21 $end
$var reg 1 } write22 $end
$var reg 1 ~ write23 $end
$var reg 1 !" write24 $end
$var reg 1 "" write25 $end
$var reg 1 #" write26 $end
$var reg 1 $" write27 $end
$var reg 1 %" write28 $end
$var reg 1 &" write29 $end
$var reg 1 '" write3 $end
$var reg 1 (" write30 $end
$var reg 1 )" write31 $end
$var reg 1 *" write32 $end
$var reg 1 +" write4 $end
$var reg 1 ," write5 $end
$var reg 1 -" write6 $end
$var reg 1 ." write7 $end
$var reg 1 /" write8 $end
$var reg 1 0" write9 $end
$scope module rg1 $end
$var wire 32 1" data_write [0:31] $end
$var wire 1 o write $end
$var reg 32 2" data [0:31] $end
$upscope $end
$scope module rg10 $end
$var wire 32 3" data_write [0:31] $end
$var wire 1 p write $end
$var reg 32 4" data [0:31] $end
$upscope $end
$scope module rg11 $end
$var wire 32 5" data_write [0:31] $end
$var wire 1 q write $end
$var reg 32 6" data [0:31] $end
$upscope $end
$scope module rg12 $end
$var wire 32 7" data_write [0:31] $end
$var wire 1 r write $end
$var reg 32 8" data [0:31] $end
$upscope $end
$scope module rg13 $end
$var wire 32 9" data_write [0:31] $end
$var wire 1 s write $end
$var reg 32 :" data [0:31] $end
$upscope $end
$scope module rg14 $end
$var wire 32 ;" data_write [0:31] $end
$var wire 1 t write $end
$var reg 32 <" data [0:31] $end
$upscope $end
$scope module rg15 $end
$var wire 32 =" data_write [0:31] $end
$var wire 1 u write $end
$var reg 32 >" data [0:31] $end
$upscope $end
$scope module rg16 $end
$var wire 32 ?" data_write [0:31] $end
$var wire 1 v write $end
$var reg 32 @" data [0:31] $end
$upscope $end
$scope module rg17 $end
$var wire 32 A" data_write [0:31] $end
$var wire 1 w write $end
$var reg 32 B" data [0:31] $end
$upscope $end
$scope module rg18 $end
$var wire 32 C" data_write [0:31] $end
$var wire 1 x write $end
$var reg 32 D" data [0:31] $end
$upscope $end
$scope module rg19 $end
$var wire 32 E" data_write [0:31] $end
$var wire 1 y write $end
$var reg 32 F" data [0:31] $end
$upscope $end
$scope module rg2 $end
$var wire 32 G" data_write [0:31] $end
$var wire 1 z write $end
$var reg 32 H" data [0:31] $end
$upscope $end
$scope module rg20 $end
$var wire 32 I" data_write [0:31] $end
$var wire 1 { write $end
$var reg 32 J" data [0:31] $end
$upscope $end
$scope module rg21 $end
$var wire 32 K" data_write [0:31] $end
$var wire 1 | write $end
$var reg 32 L" data [0:31] $end
$upscope $end
$scope module rg22 $end
$var wire 32 M" data_write [0:31] $end
$var wire 1 } write $end
$var reg 32 N" data [0:31] $end
$upscope $end
$scope module rg23 $end
$var wire 32 O" data_write [0:31] $end
$var wire 1 ~ write $end
$var reg 32 P" data [0:31] $end
$upscope $end
$scope module rg24 $end
$var wire 32 Q" data_write [0:31] $end
$var wire 1 !" write $end
$var reg 32 R" data [0:31] $end
$upscope $end
$scope module rg25 $end
$var wire 32 S" data_write [0:31] $end
$var wire 1 "" write $end
$var reg 32 T" data [0:31] $end
$upscope $end
$scope module rg26 $end
$var wire 32 U" data_write [0:31] $end
$var wire 1 #" write $end
$var reg 32 V" data [0:31] $end
$upscope $end
$scope module rg27 $end
$var wire 32 W" data_write [0:31] $end
$var wire 1 $" write $end
$var reg 32 X" data [0:31] $end
$upscope $end
$scope module rg28 $end
$var wire 32 Y" data_write [0:31] $end
$var wire 1 %" write $end
$var reg 32 Z" data [0:31] $end
$upscope $end
$scope module rg29 $end
$var wire 32 [" data_write [0:31] $end
$var wire 1 &" write $end
$var reg 32 \" data [0:31] $end
$upscope $end
$scope module rg3 $end
$var wire 32 ]" data_write [0:31] $end
$var wire 1 '" write $end
$var reg 32 ^" data [0:31] $end
$upscope $end
$scope module rg30 $end
$var wire 32 _" data_write [0:31] $end
$var wire 1 (" write $end
$var reg 32 `" data [0:31] $end
$upscope $end
$scope module rg31 $end
$var wire 32 a" data_write [0:31] $end
$var wire 1 )" write $end
$var reg 32 b" data [0:31] $end
$upscope $end
$scope module rg32 $end
$var wire 32 c" data_write [0:31] $end
$var wire 1 *" write $end
$var reg 32 d" data [0:31] $end
$upscope $end
$scope module rg4 $end
$var wire 32 e" data_write [0:31] $end
$var wire 1 +" write $end
$var reg 32 f" data [0:31] $end
$upscope $end
$scope module rg5 $end
$var wire 32 g" data_write [0:31] $end
$var wire 1 ," write $end
$var reg 32 h" data [0:31] $end
$upscope $end
$scope module rg6 $end
$var wire 32 i" data_write [0:31] $end
$var wire 1 -" write $end
$var reg 32 j" data [0:31] $end
$upscope $end
$scope module rg7 $end
$var wire 32 k" data_write [0:31] $end
$var wire 1 ." write $end
$var reg 32 l" data [0:31] $end
$upscope $end
$scope module rg8 $end
$var wire 32 m" data_write [0:31] $end
$var wire 1 /" write $end
$var reg 32 n" data [0:31] $end
$upscope $end
$scope module rg9 $end
$var wire 32 o" data_write [0:31] $end
$var wire 1 0" write $end
$var reg 32 p" data [0:31] $end
$upscope $end
$upscope $end
$upscope $end
$enddefinitions $end
#0
$dumpvars
b0 p"
bx o"
b0 n"
bx m"
b0 l"
bx k"
b0 j"
bx i"
b0 h"
bx g"
b0 f"
bx e"
b0 d"
bx c"
b0 b"
bx a"
b0 `"
bx _"
b0 ^"
bx ]"
b0 \"
bx ["
b0 Z"
bx Y"
b0 X"
bx W"
b0 V"
bx U"
b0 T"
bx S"
b0 R"
bx Q"
b0 P"
bx O"
b0 N"
bx M"
b0 L"
bx K"
b0 J"
bx I"
b0 H"
bx G"
b0 F"
bx E"
b0 D"
bx C"
b0 B"
bx A"
b0 @"
bx ?"
b0 >"
bx ="
b0 <"
bx ;"
b0 :"
bx 9"
b0 8"
bx 7"
b0 6"
bx 5"
b0 4"
bx 3"
b0 2"
b0 1"
x0"
x/"
x."
x-"
x,"
x+"
x*"
x)"
x("
x'"
x&"
x%"
x$"
x#"
x""
x!"
x~
x}
x|
x{
xz
xy
xx
xw
xv
xu
xt
xs
xr
xq
xp
1o
bx n
bx m
bx l
bx k
bx j
bx i
bx h
bx g
bx f
bx e
bx d
bx c
bx b
bx a
bx `
bx _
bx ^
bx ]
bx \
bx [
bx Z
bx Y
bx X
bx W
bx V
bx U
bx T
bx S
bx R
bx Q
bx P
bx O
bx N
b0 M
b0 L
b0 K
b0 J
b0 I
b0 H
b0 G
b0 F
b0 E
b0 D
b0 C
b0 B
b0 A
b0 @
b0 ?
b0 >
b0 =
b0 <
b0 ;
b0 :
b0 9
b0 8
b0 7
b0 6
b0 5
b0 4
b0 3
b0 2
b0 1
b0 0
b0 /
b0 .
b0 -
b0 ,
b0 +
b0 *
b0 )
b0 (
1'
b0 &
b0 %
b0 $
b0 #
bx "
bx !
$end
#10
b0 !
b0 n
b0 "
b0 m
0o
0'
#20
b1 &
b1 ,
#30
b1 %
b1 +
#40
b1 A
b1 H"
b1 X
b1 G"
1z
b1 (
1'
#50
0'
#60
b10 &
b10 ,
#70
b10 %
b10 +
#80
b10 6
b10 ^"
b10 c
b10 ]"
1'"
b10 (
1'
#90
0'
#100
b11 &
b11 ,
#110
b11 %
b11 +
#120
b11 2
b11 f"
b11 g
b11 e"
1+"
b11 (
1'
#130
0'
#140
b100 &
b100 ,
#150
b100 %
b100 +
#160
b100 1
b100 h"
b100 h
b100 g"
1,"
b100 (
1'
#170
0'
#180
b101 &
b101 ,
#190
b101 %
b101 +
#200
b101 0
b101 j"
b101 i
b101 i"
1-"
b101 (
1'
#210
0'
#220
b110 &
b110 ,
#230
b110 %
b110 +
#240
b110 /
b110 l"
b110 j
b110 k"
1."
b110 (
1'
#250
0'
#260
b111 &
b111 ,
#270
b111 %
b111 +
#280
b111 .
b111 n"
b111 k
b111 m"
1/"
b111 (
1'
#290
0'
#300
b1000 &
b1000 ,
#310
b1000 %
b1000 +
#320
b1000 -
b1000 p"
b1000 l
b1000 o"
10"
b1000 (
1'
#330
0'
#340
b1001 &
b1001 ,
#350
b1001 %
b1001 +
#360
b1001 K
b1001 4"
b1001 N
b1001 3"
1p
b1001 (
1'
#370
0'
#380
b1010 &
b1010 ,
#390
b1010 %
b1010 +
#400
b1010 J
b1010 6"
b1010 O
b1010 5"
1q
b1010 (
1'
#410
0'
#420
b1011 &
b1011 ,
#430
b1011 %
b1011 +
#440
b1011 I
b1011 8"
b1011 P
b1011 7"
1r
b1011 (
1'
#450
0'
#460
b1100 &
b1100 ,
#470
b1100 %
b1100 +
#480
b1100 H
b1100 :"
b1100 Q
b1100 9"
1s
b1100 (
1'
#490
0'
#500
b1101 &
b1101 ,
#510
b1101 %
b1101 +
#520
b1101 G
b1101 <"
b1101 R
b1101 ;"
1t
b1101 (
1'
#530
0'
#540
b1110 &
b1110 ,
#550
b1110 %
b1110 +
#560
b1110 F
b1110 >"
b1110 S
b1110 ="
1u
b1110 (
1'
#570
0'
#580
b1111 &
b1111 ,
#590
b1111 %
b1111 +
#600
b1111 E
b1111 @"
b1111 T
b1111 ?"
1v
b1111 (
1'
#610
0'
#620
b10000 &
b10000 ,
#630
b10000 %
b10000 +
#640
b10000 D
b10000 B"
b10000 U
b10000 A"
1w
b10000 (
1'
#650
0'
#660
b10001 &
b10001 ,
#670
b10001 %
b10001 +
#680
b10001 C
b10001 D"
b10001 V
b10001 C"
1x
b10001 (
1'
#690
0'
#700
b10010 &
b10010 ,
#710
b10010 %
b10010 +
#720
b10010 B
b10010 F"
b10010 W
b10010 E"
1y
b10010 (
1'
#730
0'
#740
b10011 &
b10011 ,
#750
b10011 %
b10011 +
#760
b10011 @
b10011 J"
b10011 Y
b10011 I"
1{
b10011 (
1'
#770
0'
#780
b10100 &
b10100 ,
#790
b10100 %
b10100 +
#800
b10100 ?
b10100 L"
b10100 Z
b10100 K"
1|
b10100 (
1'
#810
0'
#820
b10101 &
b10101 ,
#830
b10101 %
b10101 +
#840
b10101 >
b10101 N"
b10101 [
b10101 M"
1}
b10101 (
1'
#850
0'
#860
b10110 &
b10110 ,
#870
b10110 %
b10110 +
#880
b10110 =
b10110 P"
b10110 \
b10110 O"
1~
b10110 (
1'
#890
0'
#900
b10111 &
b10111 ,
#910
b10111 %
b10111 +
#920
b10111 <
b10111 R"
b10111 ]
b10111 Q"
1!"
b10111 (
1'
#930
0'
#940
b11000 &
b11000 ,
#950
b11000 %
b11000 +
#960
b11000 ;
b11000 T"
b11000 ^
b11000 S"
1""
b11000 (
1'
#970
0'
#980
b11001 &
b11001 ,
#990
b11001 %
b11001 +
#1000
b11001 :
b11001 V"
b11001 _
b11001 U"
1#"
b11001 (
1'
#1010
0'
#1020
b11010 &
b11010 ,
#1030
b11010 %
b11010 +
#1040
b11010 9
b11010 X"
b11010 `
b11010 W"
1$"
b11010 (
1'
#1050
0'
#1060
b11011 &
b11011 ,
#1070
b11011 %
b11011 +
#1080
b11011 8
b11011 Z"
b11011 a
b11011 Y"
1%"
b11011 (
1'
#1090
0'
#1100
b11100 &
b11100 ,
#1110
b11100 %
b11100 +
#1120
b11100 7
b11100 \"
b11100 b
b11100 ["
1&"
b11100 (
1'
#1130
0'
#1140
b11101 &
b11101 ,
#1150
b11101 %
b11101 +
#1160
b11101 5
b11101 `"
b11101 d
b11101 _"
1("
b11101 (
1'
#1170
0'
#1180
b11110 &
b11110 ,
#1190
b11110 %
b11110 +
#1200
b11110 4
b11110 b"
b11110 e
b11110 a"
1)"
b11110 (
1'
#1210
0'
#1220
b11111 &
b11111 ,
#1230
b11111 %
b11111 +
#1240
b11111 3
b11111 d"
b11111 f
b11111 c"
1*"
b11111 (
1'
#1340
0'
#1360
b1 !
b1 n
0z
b111001110011100111111110011110 %
b111001110011100111111110011110 +
b0 &
b0 ,
b1 $
b1 *
#1460
b111001110011100111111110011110 L
b111001110011100111111110011110 2"
b111001110011100111111110011110 M
b111001110011100111111110011110 1"
1o
1'
#1560
b111001110011100111111110011110 "
b111001110011100111111110011110 m
0o
0'
#1660
b11000000000100000000010000100000 %
b11000000000100000000010000100000 +
b1 &
b1 ,
#1760
b11000000000100000000010000100000 A
b11000000000100000000010000100000 H"
b11000000000100000000010000100000 X
b11000000000100000000010000100000 G"
1z
1'
#1860
b11000000000100000000010000100000 !
b11000000000100000000010000100000 n
0z
0'
